{
  "id": "worksheet_design.no_visible_solutions",
  "version": 2,
  "scope": "worksheet_design",
  "stages": ["content_mirror", "image_spec"],
  "priority": 95,
  "title": "Loesungen nicht auf dem Arbeitsblatt",
  "appliesWhen": {
    "always": true
  },
  "instructions": [
    "Loesungen, erwartete Antworten und Musterloesungen duerfen auf einer normalen Arbeitsblattseite nicht sichtbar sein.",
    "Loesungshinweise gehoeren in `expectedAnswer`, `solutionNotes` oder ein explizit angefordertes Loesungsblatt."
  ],
  "contentInstructions": [
    "Trenne sichtbare Aufgaben strikt von erwarteten Antworten."
  ],
  "imageSpecInstructions": [
    "Uebertrage keine konkreten Loesungstexte, erwarteten Antworten oder Musterloesungen in die Bildplanung.",
    "Der normale Bildprompt erhaelt nur die Regel, dass Loesungen nicht sichtbar sein duerfen."
  ],
  "imagePromptInstructions": [
    "Keine Loesungen, Musterantworten oder Erwartungshorizonte sichtbar machen.",
    "Keine konkreten Loesungstexte im normalen Bildprompt nutzen."
  ]
}
